zellij/__init__.py
zellij/core/__init__.py
zellij/core/addons.py
zellij/core/geometry.py
zellij/core/loss_func.py
zellij/core/metaheuristic.py
zellij/core/objective.py
zellij/core/observer.py
zellij/core/search_space.py
zellij/core/variables.py
zellij/strategies/__init__.py
zellij/strategies/bayesian_optimization.py
zellij/strategies/chaos_algorithm.py
zellij/strategies/dba.py
zellij/strategies/genetic_algorithm.py
zellij/strategies/ils.py
zellij/strategies/phs.py
zellij/strategies/sampling.py
zellij/strategies/simulated_annealing.py
zellij/strategies/tools/__init__.py
zellij/strategies/tools/chaos_map.py
zellij/strategies/tools/cooling.py
zellij/strategies/tools/direct_utils.py
zellij/strategies/tools/scoring.py
zellij/strategies/tools/spoke_dart.py
zellij/strategies/tools/tree_search.py
zellij/utils/__init__.py
zellij/utils/benchmarks.py
zellij/utils/converters.py
zellij/utils/distances.py
zellij/utils/neighborhoods.py
zellij/utils/operators.py
zellij/utils/progress_bar.py
zellij-1.0.1.dist-info/AUTHORS.txt
zellij-1.0.1.dist-info/LICENSE.txt
zellij-1.0.1.dist-info/METADATA
zellij-1.0.1.dist-info/WHEEL
zellij-1.0.1.dist-info/top_level.txt
zellij-1.0.1.dist-info/RECORD
