Metadata-Version: 2.1
Name: zellij
Version: 1.0.1
Summary: A software framework for HyperParameters Optimization
Home-page: https://github.com/ThomasFirmin/zellij
Author: Thomas Firmin
Author-email: thomas.firmin@univ-lille.fr
Project-URL: Bug Tracker, https://github.com/ThomasFirmin/zellij/issues
Keywords: fractal,continuous optimization,global optimization,black-box functions,decision space partitioning,exploration,exploitation,metaheuristics,tree search
Classifier: Programming Language :: Python :: 3
Classifier: License :: CeCILL-C Free Software License Agreement (CECILL-C)
Classifier: Operating System :: OS Independent
Requires-Python: >=3.6
License-File: LICENSE.txt
License-File: AUTHORS.txt
Requires-Dist: numpy (>=1.21.4)
Requires-Dist: scipy (>=1.7.3)
Requires-Dist: DEAP (>=1.3.1)
Requires-Dist: botorch (>=0.6.3.1)
Requires-Dist: gpytorch (>=1.6.0)
Requires-Dist: pandas (>=1.3.4)
Requires-Dist: enlighten (>=1.10.2)
Provides-Extra: docs
Requires-Dist: Sphinx (>=3.0.0) ; extra == 'docs'
Requires-Dist: docutils ; extra == 'docs'
Requires-Dist: pylons-sphinx-themes (>=1.0.8) ; extra == 'docs'
Requires-Dist: pylons-sphinx-latesturl ; extra == 'docs'
Requires-Dist: repoze.sphinx.autointerface ; extra == 'docs'
Requires-Dist: sphinxcontrib-autoprogram ; extra == 'docs'
Requires-Dist: sphinx-copybutton ; extra == 'docs'
Requires-Dist: sphinx-tabs ; extra == 'docs'
Requires-Dist: sphinx-panels ; extra == 'docs'
Requires-Dist: sphinx-rtd-theme ; extra == 'docs'
Requires-Dist: pillow (>=6.2.0) ; extra == 'docs'
Provides-Extra: mpi
Requires-Dist: mpi4py (>=3.1.2) ; extra == 'mpi'
